hoppr_openssf_scorecard/__init__.py
hoppr_openssf_scorecard/_helpers/__init__.py
hoppr_openssf_scorecard/_helpers/_base.py
hoppr_openssf_scorecard/_helpers/_deb.py
hoppr_openssf_scorecard/_helpers/_gem.py
hoppr_openssf_scorecard/_helpers/_git.py
hoppr_openssf_scorecard/_helpers/_github.py
hoppr_openssf_scorecard/_helpers/_gitlab.py
hoppr_openssf_scorecard/_helpers/_golang.py
hoppr_openssf_scorecard/_helpers/_helm.py
hoppr_openssf_scorecard/_helpers/_libraries.py
hoppr_openssf_scorecard/_helpers/_maven.py
hoppr_openssf_scorecard/_helpers/_npm.py
hoppr_openssf_scorecard/_helpers/_pypi.py
hoppr_openssf_scorecard/_helpers/_rpm.py
hoppr_openssf_scorecard/_helpers/py.typed
hoppr_openssf_scorecard/models/__init__.py
hoppr_openssf_scorecard/models/libraries.py
hoppr_openssf_scorecard/models/py.typed
hoppr_openssf_scorecard/models/scorecard.py
hoppr_openssf_scorecard/models/types.py
hoppr_openssf_scorecard/plugin.py
hoppr_openssf_scorecard/py.typed
hoppr_openssf_scorecard-0.0.2.dist-info/LICENSE
hoppr_openssf_scorecard-0.0.2.dist-info/METADATA
hoppr_openssf_scorecard-0.0.2.dist-info/WHEEL
hoppr_openssf_scorecard-0.0.2.dist-info/entry_points.txt
hoppr_openssf_scorecard-0.0.2.dist-info/RECORD
