Metadata-Version: 2.1
Name: hoppr-openssf-scorecard
Version: 0.0.2
Summary: Hoppr plugin to generate an OpenSSF scorecard
Home-page: https://hoppr.dev
License: MIT
Keywords: hoppr,plugin,openssf,scorecard
Author: LMCO Open Source
Author-email: open.source@lmco.com
Requires-Python: >=3.10,<4.0
Classifier: Development Status :: 2 - Pre-Alpha
Classifier: Framework :: Pydantic
Classifier: Framework :: Pytest
Classifier: Framework :: Trio
Classifier: Intended Audience :: Developers
Classifier: Intended Audience :: Information Technology
Classifier: Intended Audience :: System Administrators
Classifier: License :: OSI Approved :: MIT License
Classifier: Programming Language :: Python
Classifier: Programming Language :: Python :: 3
Classifier: Programming Language :: Python :: 3.10
Classifier: Programming Language :: Python :: 3.11
Classifier: Programming Language :: Python :: 3.12
Classifier: Topic :: Communications :: File Sharing
Classifier: Topic :: Security
Classifier: Topic :: Software Development :: Version Control
Classifier: Topic :: System :: Archiving :: Packaging
Classifier: Topic :: System :: Software Distribution
Classifier: Typing :: Typed
Requires-Dist: hoppr (>=1.9.5,<2.0.0)
Requires-Dist: hoppr-cyclonedx-models (==0.*)
Requires-Dist: httpx (==0.*)
Requires-Dist: jmespath (>=1.0.1,<2.0.0)
Requires-Dist: packageurl-python (==0.*)
Requires-Dist: pydantic (>=1.10.6,<2.0.0)
Requires-Dist: trio (==0.*)
Requires-Dist: xmltodict (==0.*)
Project-URL: Repository, https://gitlab.com/hoppr/plugins/hoppr-openssf-scorecard-plugin
